operagxdriver/README.MD
operagxdriver/__init__.py
operagxdriver/requirements.txt
operagxdriver/thirdparty.json
operagxdriver-0.10.dist-info/LICENSE.rst
operagxdriver-0.10.dist-info/METADATA
operagxdriver-0.10.dist-info/WHEEL
operagxdriver-0.10.dist-info/top_level.txt
operagxdriver-0.10.dist-info/RECORD
