Metadata-Version: 2.1
Name: operagxdriver
Version: 0.10
Summary: OperaGx webdriver with cdc patch.
Home-page: https://github.com/hansalemaos/operagxdriver
Author: Johannes Fischer
Author-email: aulasparticularesdealemaosp@gmail.com
License: MIT
Keywords: OperaGx,Selenium,webdriver
Classifier: Development Status :: 4 - Beta
Classifier: Programming Language :: Python :: 3 :: Only
Classifier: Programming Language :: Python :: 3.10
Classifier: Topic :: Software Development :: Libraries :: Python Modules
Classifier: Topic :: Utilities
License-File: LICENSE.rst
Requires-Dist: selenium
